{
  "project_info": {
    "project_number": "228130483753",
    "firebase_url": "https://trackmybullion-d15ef.firebaseio.com",
    "project_id": "trackmybullion-d15ef",
    "storage_bucket": "trackmybullion-d15ef.appspot.com"
  },
  "client": [
    {
      "client_info": {
        "mobilesdk_app_id": "1:228130483753:android:b5f60cfcebee5631",
        "android_client_info": {
          "package_name": "com.bhadrasoft.trackmybullion"
        }
      },
      "oauth_client": [
        {
          "client_id": "228130483753-rmodnm5tpd3k7349hc5trv5quvj2khvh.apps.googleusercontent.com",
          "client_type": 1,
          "android_info": {
            "package_name": "com.bhadrasoft.trackmybullion",
            "certificate_hash": "73f6e2e52434a0e010f3a7ec24f308eb720fddde"
          }
        },
        {
          "client_id": "228130483753-697d1ki517vj8kgkg83o47pdo6eu5q79.apps.googleusercontent.com",
          "client_type": 3
        }
      ],
      "api_key": [
        {
          "current_key": "AIzaSyAddnqQEdpb4BWtccKELjV8gnqoYWp9ur0"
        }
      ],
      "services": {
        "analytics_service": {
          "status": 1
        },
        "appinvite_service": {
          "status": 2,
          "other_platform_oauth_client": [
            {
              "client_id": "228130483753-697d1ki517vj8kgkg83o47pdo6eu5q79.apps.googleusercontent.com",
              "client_type": 3
            }
          ]
        },
        "ads_service": {
          "status": 2
        }
      }
    }
  ],
  "configuration_version": "1"
}